scidmg/__init__.py
scidmg/__main__.py
scidmg/base.py
scidmg-1.0.0.data/data/LICENSE
scidmg-1.0.0.dist-info/LICENSE
scidmg-1.0.0.dist-info/METADATA
scidmg-1.0.0.dist-info/WHEEL
scidmg-1.0.0.dist-info/entry_points.txt
scidmg-1.0.0.dist-info/top_level.txt
scidmg-1.0.0.dist-info/RECORD
