Metadata-Version: 2.1
Name: scidmg
Version: 1.0.0
Summary: UNKNOWN
Home-page: https://github.com/ArianeMora/scidmg
Author: Ariane Mora
Author-email: ariane.n.mora@gmail.com
License: GPL3
Project-URL: Bug Tracker, https://github.com/ArianeMora/scidmg/issues
Project-URL: Documentation, https://github.com/ArianeMora/scidmg
Project-URL: Source Code, https://github.com/ArianeMora/scidmg
Keywords: epigenetics,bioinformatics,dna-methylation
Platform: UNKNOWN
Classifier: Intended Audience :: Science/Research
Classifier: License :: OSI Approved :: GNU General Public License v3 (GPLv3)
Classifier: Natural Language :: English
Classifier: Operating System :: OS Independent
Classifier: Programming Language :: Python :: 3.6
Classifier: Programming Language :: Python :: 3.7
Classifier: Programming Language :: Python :: 3.8
Classifier: Topic :: Scientific/Engineering :: Bio-Informatics
Requires-Python: >=3.6
Requires-Dist: pandas
Requires-Dist: numpy
Requires-Dist: sciutil (>=1.0.3)
